{"id":"scripts\\model.js","dependencies":[{"name":"C:\\Users\\arnie\\Desktop\\工研院\\Music-Gerne-Classifier\\package.json","includedInParent":true,"mtime":1535467067852},{"name":"C:\\Users\\arnie\\Desktop\\工研院\\Music-Gerne-Classifier\\.babelrc","includedInParent":true,"mtime":1535334656592},{"name":"babel-runtime/regenerator","parent":"C:\\Users\\arnie\\Desktop\\工研院\\Music-Gerne-Classifier\\public\\scripts\\model.js","resolved":"C:\\Users\\arnie\\Desktop\\工研院\\Music-Gerne-Classifier\\node_modules\\babel-runtime\\regenerator\\index.js"},{"name":"babel-runtime/helpers/asyncToGenerator","parent":"C:\\Users\\arnie\\Desktop\\工研院\\Music-Gerne-Classifier\\public\\scripts\\model.js","resolved":"C:\\Users\\arnie\\Desktop\\工研院\\Music-Gerne-Classifier\\node_modules\\babel-runtime\\helpers\\asyncToGenerator.js"},{"name":"@tensorflow/tfjs","loc":{"line":1,"column":20},"parent":"C:\\Users\\arnie\\Desktop\\工研院\\Music-Gerne-Classifier\\public\\scripts\\model.js","resolved":"C:\\Users\\arnie\\Desktop\\工研院\\Music-Gerne-Classifier\\node_modules\\@tensorflow\\tfjs\\dist\\tf.esm.js"},{"name":"./config.js","loc":{"line":6,"column":7},"parent":"C:\\Users\\arnie\\Desktop\\工研院\\Music-Gerne-Classifier\\public\\scripts\\model.js","resolved":"C:\\Users\\arnie\\Desktop\\工研院\\Music-Gerne-Classifier\\public\\scripts\\config.js"},{"name":"./data","loc":{"line":8,"column":24},"parent":"C:\\Users\\arnie\\Desktop\\工研院\\Music-Gerne-Classifier\\public\\scripts\\model.js","resolved":"C:\\Users\\arnie\\Desktop\\工研院\\Music-Gerne-Classifier\\public\\scripts\\data.js"}],"generated":{"js":"'use strict';\n\nObject.defineProperty(exports, \"__esModule\", {\n    value: true\n});\nexports.train = exports.predict = exports.loadMobileNet = undefined;\n\nvar _regenerator = require('babel-runtime/regenerator');\n\nvar _regenerator2 = _interopRequireDefault(_regenerator);\n\nvar _asyncToGenerator2 = require('babel-runtime/helpers/asyncToGenerator');\n\nvar _asyncToGenerator3 = _interopRequireDefault(_asyncToGenerator2);\n\nvar loadMobileNet = exports.loadMobileNet = function () {\n    var _ref = (0, _asyncToGenerator3.default)( /*#__PURE__*/_regenerator2.default.mark(function _callee() {\n        return _regenerator2.default.wrap(function _callee$(_context) {\n            while (1) {\n                switch (_context.prev = _context.next) {\n                    case 0:\n                        _context.next = 2;\n                        return tf.loadFrozenModel(MODEL_URL, WEIGHTS_URL);\n\n                    case 2:\n                        truncModel = _context.sent;\n\n                    case 3:\n                    case 'end':\n                        return _context.stop();\n                }\n            }\n        }, _callee, this);\n    }));\n\n    return function loadMobileNet() {\n        return _ref.apply(this, arguments);\n    };\n}();\n\nvar predict = exports.predict = function () {\n    var _ref2 = (0, _asyncToGenerator3.default)( /*#__PURE__*/_regenerator2.default.mark(function _callee2(dataArray) {\n        var predictedClass, classId;\n        return _regenerator2.default.wrap(function _callee2$(_context2) {\n            while (1) {\n                switch (_context2.prev = _context2.next) {\n                    case 0:\n                        predictedClass = tf.tidy(function () {\n                            var activation = getActivation(dataArray);\n                            var predictions = model.predict(activation);\n                            _data.myDataset.addHistory(predictions);\n                            return predictions.as1D().argMax();\n                        });\n                        _context2.next = 3;\n                        return predictedClass.data();\n\n                    case 3:\n                        classId = _context2.sent[0];\n\n                        predictedClass.dispose();\n                        console.log(classId);\n                        return _context2.abrupt('return', classId);\n\n                    case 7:\n                    case 'end':\n                        return _context2.stop();\n                }\n            }\n        }, _callee2, this);\n    }));\n\n    return function predict(_x) {\n        return _ref2.apply(this, arguments);\n    };\n}();\n\nvar train = exports.train = function () {\n    var _ref3 = (0, _asyncToGenerator3.default)( /*#__PURE__*/_regenerator2.default.mark(function _callee5(dataset, setLines) {\n        var _this = this;\n\n        return _regenerator2.default.wrap(function _callee5$(_context5) {\n            while (1) {\n                switch (_context5.prev = _context5.next) {\n                    case 0:\n\n                        model.fit(dataset.xs, dataset.ys, {\n                            validationSplit: 0.1,\n                            batchSize: 5,\n                            epochs: 10,\n                            callbacks: {\n                                onEpochEnd: function () {\n                                    var _ref4 = (0, _asyncToGenerator3.default)( /*#__PURE__*/_regenerator2.default.mark(function _callee3(epoch, logs) {\n                                        return _regenerator2.default.wrap(function _callee3$(_context3) {\n                                            while (1) {\n                                                switch (_context3.prev = _context3.next) {\n                                                    case 0:\n                                                        console.log(logs, epoch);\n                                                        setLines(logs.loss, logs.val_loss, epoch);\n                                                        _context3.next = 4;\n                                                        return tf.nextFrame();\n\n                                                    case 4:\n                                                    case 'end':\n                                                        return _context3.stop();\n                                                }\n                                            }\n                                        }, _callee3, _this);\n                                    }));\n\n                                    function onEpochEnd(_x4, _x5) {\n                                        return _ref4.apply(this, arguments);\n                                    }\n\n                                    return onEpochEnd;\n                                }(),\n                                onBatchEnd: function () {\n                                    var _ref5 = (0, _asyncToGenerator3.default)( /*#__PURE__*/_regenerator2.default.mark(function _callee4(batch, logs) {\n                                        return _regenerator2.default.wrap(function _callee4$(_context4) {\n                                            while (1) {\n                                                switch (_context4.prev = _context4.next) {\n                                                    case 0:\n                                                        console.log(logs);\n                                                        console.log('Loss: ' + logs.loss.toFixed(5));\n                                                        _context4.next = 4;\n                                                        return tf.nextFrame();\n\n                                                    case 4:\n                                                    case 'end':\n                                                        return _context4.stop();\n                                                }\n                                            }\n                                        }, _callee4, _this);\n                                    }));\n\n                                    function onBatchEnd(_x6, _x7) {\n                                        return _ref5.apply(this, arguments);\n                                    }\n\n                                    return onBatchEnd;\n                                }()\n                            }\n                        });\n\n                    case 1:\n                    case 'end':\n                        return _context5.stop();\n                }\n            }\n        }, _callee5, this);\n    }));\n\n    return function train(_x2, _x3) {\n        return _ref3.apply(this, arguments);\n    };\n}();\n\nexports.getActivation = getActivation;\n\nvar _tfjs = require('@tensorflow/tfjs');\n\nvar tf = _interopRequireWildcard(_tfjs);\n\nvar _config = require('./config.js');\n\nvar _data = require('./data');\n\nfunction _interopRequireWildcard(obj) { if (obj && obj.__esModule) { return obj; } else { var newObj = {}; if (obj != null) { for (var key in obj) { if (Object.prototype.hasOwnProperty.call(obj, key)) newObj[key] = obj[key]; } } newObj.default = obj; return newObj; } }\n\nfunction _interopRequireDefault(obj) { return obj && obj.__esModule ? obj : { default: obj }; }\n\nvar MODEL_URL = 'http://localhost:3000/truncated_model/tensorflowjs_model.pb';\nvar WEIGHTS_URL = 'http://localhost:3000/truncated_model/weights_manifest.json';\n\nvar model = void 0;\nvar truncModel = void 0;\n\nmodel = tf.sequential({\n    layers: [\n    // Flattens the input to a vector so we can use it in a dense layer. While\n    // technically a layer, this only performs a reshape (and has no training\n    // parameters).\n    tf.layers.flatten({ inputShape: [4, 4, 1024] }),\n    // Layer 1\n    tf.layers.dense({\n        units: 256, // 1024 is too large for tf.js \n        activation: 'relu',\n        kernelInitializer: 'varianceScaling',\n        useBias: true\n    }),\n    // Layer 2. The number of units of the last layer should correspond\n    // to the number of classes we want to predict.\n    tf.layers.dense({\n        units: _config.GENRES_NUM,\n        kernelInitializer: 'varianceScaling',\n        useBias: false,\n        activation: 'softmax'\n    })]\n});\n\nvar optimizer = tf.train.rmsprop(0.00001); // 0.1 is too big, loss will oscillate in result \nmodel.compile({ optimizer: optimizer, loss: 'categoricalCrossentropy' });\n\nfunction getActivation(dataArray) {\n    // will activation be dispose??\n\n    var activation = tf.tidy(function () {\n        var data = tf.tensor3d(dataArray, [1, 128, 128]); // arr --> tensor\n        var rgbData = tf.stack([data, data, data], 3); // --> 3 rgb channel [1, 128,]\n        var activation = truncModel.predict(rgbData);\n        return activation;\n    });\n\n    return activation;\n}","map":{"mappings":[{"generated":{"line":17,"column":88},"source":"scripts\\model.js","original":{"line":46,"column":7}},{"generated":{"line":18,"column":0},"source":"scripts\\model.js","original":{"line":46,"column":7}},{"generated":{"line":19,"column":0},"source":"scripts\\model.js","original":{"line":46,"column":7}},{"generated":{"line":20,"column":0},"source":"scripts\\model.js","original":{"line":46,"column":7}},{"generated":{"line":21,"column":0},"source":"scripts\\model.js","original":{"line":46,"column":7}},{"generated":{"line":22,"column":0},"source":"scripts\\model.js","original":{"line":46,"column":7}},{"generated":{"line":23,"column":0},"source":"scripts\\model.js","original":{"line":46,"column":7}},{"name":"tf","generated":{"line":23,"column":31},"source":"scripts\\model.js","original":{"line":47,"column":24}},{"name":"loadFrozenModel","generated":{"line":23,"column":34},"source":"scripts\\model.js","original":{"line":47,"column":27}},{"generated":{"line":23,"column":49},"source":"scripts\\model.js","original":{"line":47,"column":24}},{"name":"MODEL_URL","generated":{"line":23,"column":50},"source":"scripts\\model.js","original":{"line":47,"column":43}},{"generated":{"line":23,"column":59},"source":"scripts\\model.js","original":{"line":47,"column":24}},{"name":"WEIGHTS_URL","generated":{"line":23,"column":61},"source":"scripts\\model.js","original":{"line":47,"column":54}},{"generated":{"line":23,"column":72},"source":"scripts\\model.js","original":{"line":47,"column":24}},{"generated":{"line":23,"column":73},"source":"scripts\\model.js","original":{"line":46,"column":7}},{"generated":{"line":25,"column":0},"source":"scripts\\model.js","original":{"line":46,"column":7}},{"name":"truncModel","generated":{"line":26,"column":0},"source":"scripts\\model.js","original":{"line":47,"column":4}},{"generated":{"line":26,"column":34},"source":"scripts\\model.js","original":{"line":46,"column":7}},{"generated":{"line":28,"column":0},"source":"scripts\\model.js","original":{"line":46,"column":7}},{"generated":{"line":29,"column":0},"source":"scripts\\model.js","original":{"line":46,"column":7}},{"generated":{"line":30,"column":0},"source":"scripts\\model.js","original":{"line":46,"column":7}},{"generated":{"line":31,"column":0},"source":"scripts\\model.js","original":{"line":46,"column":7}},{"generated":{"line":32,"column":0},"source":"scripts\\model.js","original":{"line":46,"column":7}},{"generated":{"line":33,"column":0},"source":"scripts\\model.js","original":{"line":46,"column":7}},{"generated":{"line":34,"column":0},"source":"scripts\\model.js","original":{"line":46,"column":7}},{"name":"loadMobileNet","generated":{"line":36,"column":20},"source":"scripts\\model.js","original":{"line":46,"column":22}},{"generated":{"line":42,"column":89},"source":"scripts\\model.js","original":{"line":67,"column":7}},{"name":"dataArray","generated":{"line":42,"column":107},"source":"scripts\\model.js","original":{"line":67,"column":30}},{"generated":{"line":42,"column":116},"source":"scripts\\model.js","original":{"line":67,"column":7}},{"generated":{"line":43,"column":0},"source":"scripts\\model.js","original":{"line":67,"column":7}},{"generated":{"line":44,"column":0},"source":"scripts\\model.js","original":{"line":67,"column":7}},{"generated":{"line":45,"column":0},"source":"scripts\\model.js","original":{"line":67,"column":7}},{"generated":{"line":46,"column":0},"source":"scripts\\model.js","original":{"line":67,"column":7}},{"generated":{"line":47,"column":0},"source":"scripts\\model.js","original":{"line":67,"column":7}},{"name":"predictedClass","generated":{"line":48,"column":0},"source":"scripts\\model.js","original":{"line":69,"column":10}},{"generated":{"line":48,"column":38},"source":"scripts\\model.js","original":{"line":67,"column":7}},{"name":"tf","generated":{"line":48,"column":41},"source":"scripts\\model.js","original":{"line":69,"column":27}},{"name":"tidy","generated":{"line":48,"column":44},"source":"scripts\\model.js","original":{"line":69,"column":30}},{"generated":{"line":48,"column":48},"source":"scripts\\model.js","original":{"line":69,"column":27}},{"generated":{"line":48,"column":49},"source":"scripts\\model.js","original":{"line":69,"column":35}},{"generated":{"line":48,"column":61},"source":"scripts\\model.js","original":{"line":69,"column":41}},{"generated":{"line":49,"column":0},"source":"scripts\\model.js","original":{"line":70,"column":8}},{"name":"activation","generated":{"line":49,"column":32},"source":"scripts\\model.js","original":{"line":70,"column":14}},{"name":"getActivation","generated":{"line":49,"column":45},"source":"scripts\\model.js","original":{"line":70,"column":28}},{"name":"dataArray","generated":{"line":49,"column":59},"source":"scripts\\model.js","original":{"line":70,"column":42}},{"generated":{"line":49,"column":68},"source":"scripts\\model.js","original":{"line":70,"column":28}},{"generated":{"line":49,"column":69},"source":"scripts\\model.js","original":{"line":70,"column":8}},{"generated":{"line":50,"column":0},"source":"scripts\\model.js","original":{"line":71,"column":8}},{"name":"predictions","generated":{"line":50,"column":32},"source":"scripts\\model.js","original":{"line":71,"column":14}},{"name":"model","generated":{"line":50,"column":46},"source":"scripts\\model.js","original":{"line":71,"column":28}},{"name":"predict","generated":{"line":50,"column":52},"source":"scripts\\model.js","original":{"line":71,"column":34}},{"generated":{"line":50,"column":59},"source":"scripts\\model.js","original":{"line":71,"column":28}},{"name":"activation","generated":{"line":50,"column":60},"source":"scripts\\model.js","original":{"line":71,"column":42}},{"generated":{"line":50,"column":70},"source":"scripts\\model.js","original":{"line":71,"column":28}},{"generated":{"line":50,"column":71},"source":"scripts\\model.js","original":{"line":71,"column":8}},{"name":"myDataset","generated":{"line":51,"column":0},"source":"scripts\\model.js","original":{"line":72,"column":8}},{"name":"addHistory","generated":{"line":51,"column":44},"source":"scripts\\model.js","original":{"line":72,"column":18}},{"generated":{"line":51,"column":54},"source":"scripts\\model.js","original":{"line":72,"column":8}},{"name":"predictions","generated":{"line":51,"column":55},"source":"scripts\\model.js","original":{"line":72,"column":29}},{"generated":{"line":51,"column":66},"source":"scripts\\model.js","original":{"line":72,"column":8}},{"generated":{"line":52,"column":0},"source":"scripts\\model.js","original":{"line":73,"column":8}},{"name":"predictions","generated":{"line":52,"column":35},"source":"scripts\\model.js","original":{"line":73,"column":15}},{"name":"as1D","generated":{"line":52,"column":47},"source":"scripts\\model.js","original":{"line":73,"column":27}},{"generated":{"line":52,"column":51},"source":"scripts\\model.js","original":{"line":73,"column":15}},{"name":"argMax","generated":{"line":52,"column":54},"source":"scripts\\model.js","original":{"line":73,"column":34}},{"generated":{"line":52,"column":60},"source":"scripts\\model.js","original":{"line":73,"column":15}},{"generated":{"line":52,"column":62},"source":"scripts\\model.js","original":{"line":73,"column":8}},{"generated":{"line":53,"column":0},"source":"scripts\\model.js","original":{"line":74,"column":7}},{"generated":{"line":53,"column":25},"source":"scripts\\model.js","original":{"line":69,"column":27}},{"generated":{"line":53,"column":26},"source":"scripts\\model.js","original":{"line":67,"column":7}},{"generated":{"line":54,"column":0},"source":"scripts\\model.js","original":{"line":67,"column":7}},{"generated":{"line":55,"column":0},"source":"scripts\\model.js","original":{"line":67,"column":7}},{"name":"predictedClass","generated":{"line":55,"column":31},"source":"scripts\\model.js","original":{"line":76,"column":29}},{"name":"data","generated":{"line":55,"column":46},"source":"scripts\\model.js","original":{"line":76,"column":44}},{"generated":{"line":55,"column":50},"source":"scripts\\model.js","original":{"line":76,"column":29}},{"generated":{"line":55,"column":52},"source":"scripts\\model.js","original":{"line":67,"column":7}},{"generated":{"line":57,"column":0},"source":"scripts\\model.js","original":{"line":67,"column":7}},{"name":"classId","generated":{"line":58,"column":0},"source":"scripts\\model.js","original":{"line":76,"column":12}},{"generated":{"line":58,"column":31},"source":"scripts\\model.js","original":{"line":67,"column":7}},{"generated":{"line":58,"column":49},"source":"scripts\\model.js","original":{"line":76,"column":52}},{"generated":{"line":58,"column":50},"source":"scripts\\model.js","original":{"line":67,"column":7}},{"name":"predictedClass","generated":{"line":60,"column":0},"source":"scripts\\model.js","original":{"line":77,"column":6}},{"name":"dispose","generated":{"line":60,"column":39},"source":"scripts\\model.js","original":{"line":77,"column":21}},{"generated":{"line":60,"column":46},"source":"scripts\\model.js","original":{"line":77,"column":6}},{"name":"console","generated":{"line":61,"column":0},"source":"scripts\\model.js","original":{"line":78,"column":6}},{"name":"log","generated":{"line":61,"column":32},"source":"scripts\\model.js","original":{"line":78,"column":14}},{"generated":{"line":61,"column":35},"source":"scripts\\model.js","original":{"line":78,"column":6}},{"name":"classId","generated":{"line":61,"column":36},"source":"scripts\\model.js","original":{"line":78,"column":18}},{"generated":{"line":61,"column":43},"source":"scripts\\model.js","original":{"line":78,"column":6}},{"generated":{"line":62,"column":0},"source":"scripts\\model.js","original":{"line":67,"column":7}},{"name":"classId","generated":{"line":62,"column":58},"source":"scripts\\model.js","original":{"line":79,"column":13}},{"generated":{"line":62,"column":65},"source":"scripts\\model.js","original":{"line":67,"column":7}},{"generated":{"line":64,"column":0},"source":"scripts\\model.js","original":{"line":67,"column":7}},{"generated":{"line":65,"column":0},"source":"scripts\\model.js","original":{"line":67,"column":7}},{"generated":{"line":66,"column":0},"source":"scripts\\model.js","original":{"line":67,"column":7}},{"generated":{"line":67,"column":0},"source":"scripts\\model.js","original":{"line":67,"column":7}},{"generated":{"line":68,"column":0},"source":"scripts\\model.js","original":{"line":67,"column":7}},{"generated":{"line":69,"column":0},"source":"scripts\\model.js","original":{"line":67,"column":7}},{"generated":{"line":70,"column":0},"source":"scripts\\model.js","original":{"line":67,"column":7}},{"name":"predict","generated":{"line":72,"column":20},"source":"scripts\\model.js","original":{"line":67,"column":22}},{"generated":{"line":78,"column":89},"source":"scripts\\model.js","original":{"line":86,"column":7}},{"name":"dataset","generated":{"line":78,"column":107},"source":"scripts\\model.js","original":{"line":86,"column":28}},{"generated":{"line":78,"column":114},"source":"scripts\\model.js","original":{"line":86,"column":7}},{"name":"setLines","generated":{"line":78,"column":116},"source":"scripts\\model.js","original":{"line":86,"column":37}},{"generated":{"line":78,"column":124},"source":"scripts\\model.js","original":{"line":86,"column":7}},{"generated":{"line":79,"column":0},"source":"scripts\\model.js","original":{"line":86,"column":7}},{"generated":{"line":81,"column":0},"source":"scripts\\model.js","original":{"line":86,"column":7}},{"generated":{"line":82,"column":0},"source":"scripts\\model.js","original":{"line":86,"column":7}},{"generated":{"line":83,"column":0},"source":"scripts\\model.js","original":{"line":86,"column":7}},{"generated":{"line":84,"column":0},"source":"scripts\\model.js","original":{"line":86,"column":7}},{"name":"model","generated":{"line":86,"column":0},"source":"scripts\\model.js","original":{"line":88,"column":4}},{"name":"fit","generated":{"line":86,"column":30},"source":"scripts\\model.js","original":{"line":88,"column":10}},{"generated":{"line":86,"column":33},"source":"scripts\\model.js","original":{"line":88,"column":4}},{"name":"dataset","generated":{"line":86,"column":34},"source":"scripts\\model.js","original":{"line":88,"column":14}},{"name":"xs","generated":{"line":86,"column":42},"source":"scripts\\model.js","original":{"line":88,"column":22}},{"generated":{"line":86,"column":44},"source":"scripts\\model.js","original":{"line":88,"column":4}},{"name":"dataset","generated":{"line":86,"column":46},"source":"scripts\\model.js","original":{"line":88,"column":26}},{"name":"ys","generated":{"line":86,"column":54},"source":"scripts\\model.js","original":{"line":88,"column":34}},{"generated":{"line":86,"column":56},"source":"scripts\\model.js","original":{"line":88,"column":4}},{"generated":{"line":86,"column":58},"source":"scripts\\model.js","original":{"line":88,"column":38}},{"name":"validationSplit","generated":{"line":87,"column":0},"source":"scripts\\model.js","original":{"line":89,"column":12}},{"generated":{"line":87,"column":45},"source":"scripts\\model.js","original":{"line":89,"column":29}},{"generated":{"line":87,"column":48},"source":"scripts\\model.js","original":{"line":88,"column":38}},{"name":"batchSize","generated":{"line":88,"column":0},"source":"scripts\\model.js","original":{"line":90,"column":12}},{"generated":{"line":88,"column":39},"source":"scripts\\model.js","original":{"line":90,"column":23}},{"generated":{"line":88,"column":40},"source":"scripts\\model.js","original":{"line":88,"column":38}},{"name":"epochs","generated":{"line":89,"column":0},"source":"scripts\\model.js","original":{"line":91,"column":12}},{"generated":{"line":89,"column":36},"source":"scripts\\model.js","original":{"line":91,"column":20}},{"generated":{"line":89,"column":38},"source":"scripts\\model.js","original":{"line":88,"column":38}},{"name":"callbacks","generated":{"line":90,"column":0},"source":"scripts\\model.js","original":{"line":92,"column":12}},{"generated":{"line":90,"column":39},"source":"scripts\\model.js","original":{"line":92,"column":23}},{"name":"onEpochEnd","generated":{"line":91,"column":0},"source":"scripts\\model.js","original":{"line":93,"column":16}},{"generated":{"line":92,"column":0},"source":"scripts\\model.js","original":{"line":93,"column":16}},{"generated":{"line":92,"column":121},"source":"scripts\\model.js","original":{"line":93,"column":28}},{"name":"epoch","generated":{"line":92,"column":139},"source":"scripts\\model.js","original":{"line":93,"column":35}},{"generated":{"line":92,"column":144},"source":"scripts\\model.js","original":{"line":93,"column":28}},{"name":"logs","generated":{"line":92,"column":146},"source":"scripts\\model.js","original":{"line":93,"column":42}},{"generated":{"line":92,"column":150},"source":"scripts\\model.js","original":{"line":93,"column":28}},{"generated":{"line":93,"column":0},"source":"scripts\\model.js","original":{"line":93,"column":28}},{"generated":{"line":94,"column":0},"source":"scripts\\model.js","original":{"line":93,"column":28}},{"generated":{"line":95,"column":0},"source":"scripts\\model.js","original":{"line":93,"column":28}},{"generated":{"line":96,"column":0},"source":"scripts\\model.js","original":{"line":93,"column":28}},{"name":"console","generated":{"line":97,"column":0},"source":"scripts\\model.js","original":{"line":94,"column":20}},{"name":"log","generated":{"line":97,"column":64},"source":"scripts\\model.js","original":{"line":94,"column":28}},{"generated":{"line":97,"column":67},"source":"scripts\\model.js","original":{"line":94,"column":20}},{"name":"logs","generated":{"line":97,"column":68},"source":"scripts\\model.js","original":{"line":94,"column":32}},{"generated":{"line":97,"column":72},"source":"scripts\\model.js","original":{"line":94,"column":20}},{"name":"epoch","generated":{"line":97,"column":74},"source":"scripts\\model.js","original":{"line":94,"column":38}},{"generated":{"line":97,"column":79},"source":"scripts\\model.js","original":{"line":94,"column":20}},{"name":"setLines","generated":{"line":98,"column":0},"source":"scripts\\model.js","original":{"line":95,"column":20}},{"name":"logs","generated":{"line":98,"column":65},"source":"scripts\\model.js","original":{"line":95,"column":29}},{"name":"loss","generated":{"line":98,"column":70},"source":"scripts\\model.js","original":{"line":95,"column":34}},{"generated":{"line":98,"column":74},"source":"scripts\\model.js","original":{"line":95,"column":20}},{"name":"logs","generated":{"line":98,"column":76},"source":"scripts\\model.js","original":{"line":95,"column":40}},{"name":"val_loss","generated":{"line":98,"column":81},"source":"scripts\\model.js","original":{"line":95,"column":45}},{"generated":{"line":98,"column":89},"source":"scripts\\model.js","original":{"line":95,"column":20}},{"name":"epoch","generated":{"line":98,"column":91},"source":"scripts\\model.js","original":{"line":95,"column":55}},{"generated":{"line":98,"column":96},"source":"scripts\\model.js","original":{"line":95,"column":20}},{"generated":{"line":99,"column":0},"source":"scripts\\model.js","original":{"line":93,"column":28}},{"generated":{"line":100,"column":0},"source":"scripts\\model.js","original":{"line":93,"column":28}},{"name":"tf","generated":{"line":100,"column":63},"source":"scripts\\model.js","original":{"line":96,"column":26}},{"name":"nextFrame","generated":{"line":100,"column":66},"source":"scripts\\model.js","original":{"line":96,"column":29}},{"generated":{"line":100,"column":75},"source":"scripts\\model.js","original":{"line":96,"column":26}},{"generated":{"line":100,"column":77},"source":"scripts\\model.js","original":{"line":93,"column":28}},{"generated":{"line":102,"column":0},"source":"scripts\\model.js","original":{"line":93,"column":28}},{"generated":{"line":103,"column":0},"source":"scripts\\model.js","original":{"line":93,"column":28}},{"generated":{"line":104,"column":0},"source":"scripts\\model.js","original":{"line":93,"column":28}},{"generated":{"line":105,"column":0},"source":"scripts\\model.js","original":{"line":93,"column":28}},{"generated":{"line":106,"column":0},"source":"scripts\\model.js","original":{"line":93,"column":28}},{"generated":{"line":107,"column":0},"source":"scripts\\model.js","original":{"line":93,"column":28}},{"generated":{"line":108,"column":0},"source":"scripts\\model.js","original":{"line":93,"column":28}},{"generated":{"line":108,"column":37},"source":"scripts\\model.js","original":{"line":93,"column":16}},{"generated":{"line":110,"column":0},"source":"scripts\\model.js","original":{"line":93,"column":16}},{"generated":{"line":111,"column":0},"source":"scripts\\model.js","original":{"line":93,"column":16}},{"generated":{"line":112,"column":0},"source":"scripts\\model.js","original":{"line":93,"column":16}},{"generated":{"line":114,"column":0},"source":"scripts\\model.js","original":{"line":93,"column":16}},{"generated":{"line":115,"column":0},"source":"scripts\\model.js","original":{"line":93,"column":16}},{"generated":{"line":115,"column":35},"source":"scripts\\model.js","original":{"line":92,"column":23}},{"name":"onBatchEnd","generated":{"line":116,"column":0},"source":"scripts\\model.js","original":{"line":98,"column":16}},{"generated":{"line":117,"column":0},"source":"scripts\\model.js","original":{"line":98,"column":16}},{"generated":{"line":117,"column":121},"source":"scripts\\model.js","original":{"line":98,"column":28}},{"name":"batch","generated":{"line":117,"column":139},"source":"scripts\\model.js","original":{"line":98,"column":35}},{"generated":{"line":117,"column":144},"source":"scripts\\model.js","original":{"line":98,"column":28}},{"name":"logs","generated":{"line":117,"column":146},"source":"scripts\\model.js","original":{"line":98,"column":42}},{"generated":{"line":117,"column":150},"source":"scripts\\model.js","original":{"line":98,"column":28}},{"generated":{"line":118,"column":0},"source":"scripts\\model.js","original":{"line":98,"column":28}},{"generated":{"line":119,"column":0},"source":"scripts\\model.js","original":{"line":98,"column":28}},{"generated":{"line":120,"column":0},"source":"scripts\\model.js","original":{"line":98,"column":28}},{"generated":{"line":121,"column":0},"source":"scripts\\model.js","original":{"line":98,"column":28}},{"name":"console","generated":{"line":122,"column":0},"source":"scripts\\model.js","original":{"line":99,"column":20}},{"name":"log","generated":{"line":122,"column":64},"source":"scripts\\model.js","original":{"line":99,"column":28}},{"generated":{"line":122,"column":67},"source":"scripts\\model.js","original":{"line":99,"column":20}},{"name":"logs","generated":{"line":122,"column":68},"source":"scripts\\model.js","original":{"line":99,"column":32}},{"generated":{"line":122,"column":72},"source":"scripts\\model.js","original":{"line":99,"column":20}},{"name":"console","generated":{"line":123,"column":0},"source":"scripts\\model.js","original":{"line":100,"column":18}},{"name":"log","generated":{"line":123,"column":64},"source":"scripts\\model.js","original":{"line":100,"column":26}},{"generated":{"line":123,"column":67},"source":"scripts\\model.js","original":{"line":100,"column":18}},{"generated":{"line":123,"column":68},"source":"scripts\\model.js","original":{"line":100,"column":30}},{"name":"logs","generated":{"line":123,"column":79},"source":"scripts\\model.js","original":{"line":100,"column":41}},{"name":"loss","generated":{"line":123,"column":84},"source":"scripts\\model.js","original":{"line":100,"column":46}},{"generated":{"line":123,"column":88},"source":"scripts\\model.js","original":{"line":100,"column":41}},{"name":"toFixed","generated":{"line":123,"column":89},"source":"scripts\\model.js","original":{"line":100,"column":51}},{"generated":{"line":123,"column":96},"source":"scripts\\model.js","original":{"line":100,"column":41}},{"generated":{"line":123,"column":97},"source":"scripts\\model.js","original":{"line":100,"column":59}},{"generated":{"line":123,"column":98},"source":"scripts\\model.js","original":{"line":100,"column":41}},{"generated":{"line":123,"column":99},"source":"scripts\\model.js","original":{"line":100,"column":18}},{"generated":{"line":124,"column":0},"source":"scripts\\model.js","original":{"line":98,"column":28}},{"generated":{"line":125,"column":0},"source":"scripts\\model.js","original":{"line":98,"column":28}},{"name":"tf","generated":{"line":125,"column":63},"source":"scripts\\model.js","original":{"line":101,"column":24}},{"name":"nextFrame","generated":{"line":125,"column":66},"source":"scripts\\model.js","original":{"line":101,"column":27}},{"generated":{"line":125,"column":75},"source":"scripts\\model.js","original":{"line":101,"column":24}},{"generated":{"line":125,"column":77},"source":"scripts\\model.js","original":{"line":98,"column":28}},{"generated":{"line":127,"column":0},"source":"scripts\\model.js","original":{"line":98,"column":28}},{"generated":{"line":128,"column":0},"source":"scripts\\model.js","original":{"line":98,"column":28}},{"generated":{"line":129,"column":0},"source":"scripts\\model.js","original":{"line":98,"column":28}},{"generated":{"line":130,"column":0},"source":"scripts\\model.js","original":{"line":98,"column":28}},{"generated":{"line":131,"column":0},"source":"scripts\\model.js","original":{"line":98,"column":28}},{"generated":{"line":132,"column":0},"source":"scripts\\model.js","original":{"line":98,"column":28}},{"generated":{"line":133,"column":0},"source":"scripts\\model.js","original":{"line":98,"column":28}},{"generated":{"line":133,"column":37},"source":"scripts\\model.js","original":{"line":98,"column":16}},{"generated":{"line":135,"column":0},"source":"scripts\\model.js","original":{"line":98,"column":16}},{"generated":{"line":136,"column":0},"source":"scripts\\model.js","original":{"line":98,"column":16}},{"generated":{"line":137,"column":0},"source":"scripts\\model.js","original":{"line":98,"column":16}},{"generated":{"line":139,"column":0},"source":"scripts\\model.js","original":{"line":98,"column":16}},{"generated":{"line":140,"column":0},"source":"scripts\\model.js","original":{"line":98,"column":16}},{"generated":{"line":141,"column":0},"source":"scripts\\model.js","original":{"line":92,"column":23}},{"generated":{"line":142,"column":0},"source":"scripts\\model.js","original":{"line":88,"column":38}},{"generated":{"line":142,"column":25},"source":"scripts\\model.js","original":{"line":88,"column":4}},{"generated":{"line":144,"column":0},"source":"scripts\\model.js","original":{"line":86,"column":7}},{"generated":{"line":145,"column":0},"source":"scripts\\model.js","original":{"line":86,"column":7}},{"generated":{"line":146,"column":0},"source":"scripts\\model.js","original":{"line":86,"column":7}},{"generated":{"line":147,"column":0},"source":"scripts\\model.js","original":{"line":86,"column":7}},{"generated":{"line":148,"column":0},"source":"scripts\\model.js","original":{"line":86,"column":7}},{"generated":{"line":149,"column":0},"source":"scripts\\model.js","original":{"line":86,"column":7}},{"generated":{"line":150,"column":0},"source":"scripts\\model.js","original":{"line":86,"column":7}},{"name":"train","generated":{"line":152,"column":20},"source":"scripts\\model.js","original":{"line":86,"column":22}},{"name":"getActivation","generated":{"line":157,"column":8},"source":"scripts\\model.js","original":{"line":53,"column":16}},{"name":"getActivation","generated":{"line":157,"column":24},"source":"scripts\\model.js","original":{"line":53,"column":16}},{"generated":{"line":159,"column":0},"source":"scripts\\model.js","original":{"line":1,"column":0}},{"name":"tf","generated":{"line":161,"column":4},"source":"scripts\\model.js","original":{"line":1,"column":12}},{"generated":{"line":163,"column":0},"source":"scripts\\model.js","original":{"line":2,"column":0}},{"generated":{"line":165,"column":0},"source":"scripts\\model.js","original":{"line":8,"column":0}},{"generated":{"line":171,"column":0},"source":"scripts\\model.js","original":{"line":11,"column":0}},{"name":"MODEL_URL","generated":{"line":171,"column":4},"source":"scripts\\model.js","original":{"line":11,"column":6}},{"generated":{"line":171,"column":16},"source":"scripts\\model.js","original":{"line":11,"column":18}},{"generated":{"line":171,"column":77},"source":"scripts\\model.js","original":{"line":11,"column":0}},{"generated":{"line":172,"column":0},"source":"scripts\\model.js","original":{"line":12,"column":0}},{"name":"WEIGHTS_URL","generated":{"line":172,"column":4},"source":"scripts\\model.js","original":{"line":12,"column":6}},{"generated":{"line":172,"column":18},"source":"scripts\\model.js","original":{"line":12,"column":20}},{"generated":{"line":172,"column":79},"source":"scripts\\model.js","original":{"line":12,"column":0}},{"generated":{"line":174,"column":0},"source":"scripts\\model.js","original":{"line":14,"column":0}},{"name":"model","generated":{"line":174,"column":4},"source":"scripts\\model.js","original":{"line":14,"column":4}},{"generated":{"line":174,"column":18},"source":"scripts\\model.js","original":{"line":14,"column":0}},{"generated":{"line":175,"column":0},"source":"scripts\\model.js","original":{"line":15,"column":0}},{"name":"truncModel","generated":{"line":175,"column":4},"source":"scripts\\model.js","original":{"line":15,"column":4}},{"generated":{"line":175,"column":23},"source":"scripts\\model.js","original":{"line":15,"column":0}},{"name":"model","generated":{"line":177,"column":0},"source":"scripts\\model.js","original":{"line":17,"column":0}},{"name":"tf","generated":{"line":177,"column":8},"source":"scripts\\model.js","original":{"line":17,"column":8}},{"name":"sequential","generated":{"line":177,"column":11},"source":"scripts\\model.js","original":{"line":17,"column":11}},{"generated":{"line":177,"column":21},"source":"scripts\\model.js","original":{"line":17,"column":8}},{"generated":{"line":177,"column":22},"source":"scripts\\model.js","original":{"line":17,"column":22}},{"name":"layers","generated":{"line":178,"column":0},"source":"scripts\\model.js","original":{"line":18,"column":4}},{"generated":{"line":178,"column":12},"source":"scripts\\model.js","original":{"line":18,"column":12}},{"generated":{"line":179,"column":0},"source":"scripts\\model.js","original":{"line":19,"column":6}},{"generated":{"line":180,"column":0},"source":"scripts\\model.js","original":{"line":20,"column":6}},{"generated":{"line":181,"column":0},"source":"scripts\\model.js","original":{"line":21,"column":6}},{"name":"tf","generated":{"line":182,"column":0},"source":"scripts\\model.js","original":{"line":22,"column":6}},{"name":"layers","generated":{"line":182,"column":7},"source":"scripts\\model.js","original":{"line":22,"column":9}},{"generated":{"line":182,"column":13},"source":"scripts\\model.js","original":{"line":22,"column":6}},{"name":"flatten","generated":{"line":182,"column":14},"source":"scripts\\model.js","original":{"line":22,"column":16}},{"generated":{"line":182,"column":21},"source":"scripts\\model.js","original":{"line":22,"column":6}},{"generated":{"line":182,"column":22},"source":"scripts\\model.js","original":{"line":22,"column":24}},{"name":"inputShape","generated":{"line":182,"column":24},"source":"scripts\\model.js","original":{"line":22,"column":25}},{"generated":{"line":182,"column":36},"source":"scripts\\model.js","original":{"line":22,"column":37}},{"generated":{"line":182,"column":37},"source":"scripts\\model.js","original":{"line":22,"column":38}},{"generated":{"line":182,"column":38},"source":"scripts\\model.js","original":{"line":22,"column":37}},{"generated":{"line":182,"column":40},"source":"scripts\\model.js","original":{"line":22,"column":41}},{"generated":{"line":182,"column":41},"source":"scripts\\model.js","original":{"line":22,"column":37}},{"generated":{"line":182,"column":43},"source":"scripts\\model.js","original":{"line":22,"column":44}},{"generated":{"line":182,"column":47},"source":"scripts\\model.js","original":{"line":22,"column":37}},{"generated":{"line":182,"column":48},"source":"scripts\\model.js","original":{"line":22,"column":24}},{"generated":{"line":182,"column":50},"source":"scripts\\model.js","original":{"line":22,"column":6}},{"generated":{"line":182,"column":51},"source":"scripts\\model.js","original":{"line":18,"column":12}},{"generated":{"line":183,"column":0},"source":"scripts\\model.js","original":{"line":23,"column":6}},{"name":"tf","generated":{"line":184,"column":0},"source":"scripts\\model.js","original":{"line":24,"column":6}},{"name":"layers","generated":{"line":184,"column":7},"source":"scripts\\model.js","original":{"line":24,"column":9}},{"generated":{"line":184,"column":13},"source":"scripts\\model.js","original":{"line":24,"column":6}},{"name":"dense","generated":{"line":184,"column":14},"source":"scripts\\model.js","original":{"line":24,"column":16}},{"generated":{"line":184,"column":19},"source":"scripts\\model.js","original":{"line":24,"column":6}},{"generated":{"line":184,"column":20},"source":"scripts\\model.js","original":{"line":24,"column":22}},{"name":"units","generated":{"line":185,"column":0},"source":"scripts\\model.js","original":{"line":25,"column":8}},{"generated":{"line":185,"column":15},"source":"scripts\\model.js","original":{"line":25,"column":15}},{"generated":{"line":185,"column":18},"source":"scripts\\model.js","original":{"line":24,"column":22}},{"generated":{"line":185,"column":20},"source":"scripts\\model.js","original":{"line":25,"column":30}},{"name":"activation","generated":{"line":186,"column":0},"source":"scripts\\model.js","original":{"line":26,"column":8}},{"generated":{"line":186,"column":20},"source":"scripts\\model.js","original":{"line":26,"column":20}},{"generated":{"line":186,"column":26},"source":"scripts\\model.js","original":{"line":24,"column":22}},{"name":"kernelInitializer","generated":{"line":187,"column":0},"source":"scripts\\model.js","original":{"line":27,"column":8}},{"generated":{"line":187,"column":27},"source":"scripts\\model.js","original":{"line":27,"column":27}},{"generated":{"line":187,"column":44},"source":"scripts\\model.js","original":{"line":24,"column":22}},{"name":"useBias","generated":{"line":188,"column":0},"source":"scripts\\model.js","original":{"line":28,"column":8}},{"generated":{"line":188,"column":17},"source":"scripts\\model.js","original":{"line":28,"column":17}},{"generated":{"line":189,"column":0},"source":"scripts\\model.js","original":{"line":24,"column":22}},{"generated":{"line":189,"column":5},"source":"scripts\\model.js","original":{"line":24,"column":6}},{"generated":{"line":189,"column":6},"source":"scripts\\model.js","original":{"line":18,"column":12}},{"generated":{"line":190,"column":0},"source":"scripts\\model.js","original":{"line":30,"column":6}},{"generated":{"line":191,"column":0},"source":"scripts\\model.js","original":{"line":31,"column":6}},{"name":"tf","generated":{"line":192,"column":0},"source":"scripts\\model.js","original":{"line":32,"column":6}},{"name":"layers","generated":{"line":192,"column":7},"source":"scripts\\model.js","original":{"line":32,"column":9}},{"generated":{"line":192,"column":13},"source":"scripts\\model.js","original":{"line":32,"column":6}},{"name":"dense","generated":{"line":192,"column":14},"source":"scripts\\model.js","original":{"line":32,"column":16}},{"generated":{"line":192,"column":19},"source":"scripts\\model.js","original":{"line":32,"column":6}},{"generated":{"line":192,"column":20},"source":"scripts\\model.js","original":{"line":32,"column":22}},{"name":"units","generated":{"line":193,"column":0},"source":"scripts\\model.js","original":{"line":33,"column":8}},{"name":"GENRES_NUM","generated":{"line":193,"column":15},"source":"scripts\\model.js","original":{"line":33,"column":15}},{"generated":{"line":193,"column":33},"source":"scripts\\model.js","original":{"line":32,"column":22}},{"name":"kernelInitializer","generated":{"line":194,"column":0},"source":"scripts\\model.js","original":{"line":34,"column":8}},{"generated":{"line":194,"column":27},"source":"scripts\\model.js","original":{"line":34,"column":27}},{"generated":{"line":194,"column":44},"source":"scripts\\model.js","original":{"line":32,"column":22}},{"name":"useBias","generated":{"line":195,"column":0},"source":"scripts\\model.js","original":{"line":35,"column":8}},{"generated":{"line":195,"column":17},"source":"scripts\\model.js","original":{"line":35,"column":17}},{"generated":{"line":195,"column":22},"source":"scripts\\model.js","original":{"line":32,"column":22}},{"name":"activation","generated":{"line":196,"column":0},"source":"scripts\\model.js","original":{"line":36,"column":8}},{"generated":{"line":196,"column":20},"source":"scripts\\model.js","original":{"line":36,"column":20}},{"generated":{"line":197,"column":0},"source":"scripts\\model.js","original":{"line":32,"column":22}},{"generated":{"line":197,"column":5},"source":"scripts\\model.js","original":{"line":32,"column":6}},{"generated":{"line":197,"column":6},"source":"scripts\\model.js","original":{"line":18,"column":12}},{"generated":{"line":198,"column":0},"source":"scripts\\model.js","original":{"line":17,"column":22}},{"generated":{"line":198,"column":1},"source":"scripts\\model.js","original":{"line":17,"column":8}},{"generated":{"line":198,"column":2},"source":"scripts\\model.js","original":{"line":17,"column":0}},{"generated":{"line":200,"column":0},"source":"scripts\\model.js","original":{"line":41,"column":0}},{"name":"optimizer","generated":{"line":200,"column":4},"source":"scripts\\model.js","original":{"line":41,"column":6}},{"name":"tf","generated":{"line":200,"column":16},"source":"scripts\\model.js","original":{"line":41,"column":18}},{"name":"train","generated":{"line":200,"column":19},"source":"scripts\\model.js","original":{"line":41,"column":21}},{"generated":{"line":200,"column":24},"source":"scripts\\model.js","original":{"line":41,"column":18}},{"name":"rmsprop","generated":{"line":200,"column":25},"source":"scripts\\model.js","original":{"line":41,"column":27}},{"generated":{"line":200,"column":32},"source":"scripts\\model.js","original":{"line":41,"column":18}},{"generated":{"line":200,"column":33},"source":"scripts\\model.js","original":{"line":41,"column":35}},{"generated":{"line":200,"column":40},"source":"scripts\\model.js","original":{"line":41,"column":18}},{"generated":{"line":200,"column":41},"source":"scripts\\model.js","original":{"line":41,"column":0}},{"generated":{"line":200,"column":43},"source":"scripts\\model.js","original":{"line":41,"column":45}},{"name":"model","generated":{"line":201,"column":0},"source":"scripts\\model.js","original":{"line":42,"column":0}},{"name":"compile","generated":{"line":201,"column":6},"source":"scripts\\model.js","original":{"line":42,"column":6}},{"generated":{"line":201,"column":13},"source":"scripts\\model.js","original":{"line":42,"column":0}},{"generated":{"line":201,"column":14},"source":"scripts\\model.js","original":{"line":42,"column":14}},{"name":"optimizer","generated":{"line":201,"column":16},"source":"scripts\\model.js","original":{"line":42,"column":15}},{"name":"optimizer","generated":{"line":201,"column":27},"source":"scripts\\model.js","original":{"line":42,"column":26}},{"generated":{"line":201,"column":36},"source":"scripts\\model.js","original":{"line":42,"column":14}},{"name":"loss","generated":{"line":201,"column":38},"source":"scripts\\model.js","original":{"line":42,"column":37}},{"generated":{"line":201,"column":44},"source":"scripts\\model.js","original":{"line":42,"column":43}},{"generated":{"line":201,"column":69},"source":"scripts\\model.js","original":{"line":42,"column":14}},{"generated":{"line":201,"column":71},"source":"scripts\\model.js","original":{"line":42,"column":0}},{"generated":{"line":203,"column":0},"source":"scripts\\model.js","original":{"line":53,"column":7}},{"name":"getActivation","generated":{"line":203,"column":9},"source":"scripts\\model.js","original":{"line":53,"column":16}},{"generated":{"line":203,"column":22},"source":"scripts\\model.js","original":{"line":53,"column":7}},{"name":"dataArray","generated":{"line":203,"column":23},"source":"scripts\\model.js","original":{"line":53,"column":31}},{"generated":{"line":203,"column":32},"source":"scripts\\model.js","original":{"line":53,"column":7}},{"generated":{"line":203,"column":34},"source":"scripts\\model.js","original":{"line":53,"column":42}},{"generated":{"line":204,"column":0},"source":"scripts\\model.js","original":{"line":53,"column":44}},{"generated":{"line":206,"column":0},"source":"scripts\\model.js","original":{"line":55,"column":4}},{"name":"activation","generated":{"line":206,"column":8},"source":"scripts\\model.js","original":{"line":55,"column":10}},{"name":"tf","generated":{"line":206,"column":21},"source":"scripts\\model.js","original":{"line":55,"column":23}},{"name":"tidy","generated":{"line":206,"column":24},"source":"scripts\\model.js","original":{"line":55,"column":26}},{"generated":{"line":206,"column":28},"source":"scripts\\model.js","original":{"line":55,"column":23}},{"generated":{"line":206,"column":29},"source":"scripts\\model.js","original":{"line":55,"column":31}},{"generated":{"line":206,"column":41},"source":"scripts\\model.js","original":{"line":55,"column":37}},{"generated":{"line":207,"column":0},"source":"scripts\\model.js","original":{"line":56,"column":8}},{"name":"data","generated":{"line":207,"column":12},"source":"scripts\\model.js","original":{"line":56,"column":14}},{"name":"tf","generated":{"line":207,"column":19},"source":"scripts\\model.js","original":{"line":56,"column":21}},{"name":"tensor3d","generated":{"line":207,"column":22},"source":"scripts\\model.js","original":{"line":56,"column":24}},{"generated":{"line":207,"column":30},"source":"scripts\\model.js","original":{"line":56,"column":21}},{"name":"dataArray","generated":{"line":207,"column":31},"source":"scripts\\model.js","original":{"line":56,"column":33}},{"generated":{"line":207,"column":40},"source":"scripts\\model.js","original":{"line":56,"column":21}},{"generated":{"line":207,"column":42},"source":"scripts\\model.js","original":{"line":56,"column":44}},{"generated":{"line":207,"column":43},"source":"scripts\\model.js","original":{"line":56,"column":45}},{"generated":{"line":207,"column":44},"source":"scripts\\model.js","original":{"line":56,"column":44}},{"generated":{"line":207,"column":46},"source":"scripts\\model.js","original":{"line":56,"column":48}},{"generated":{"line":207,"column":49},"source":"scripts\\model.js","original":{"line":56,"column":44}},{"generated":{"line":207,"column":51},"source":"scripts\\model.js","original":{"line":56,"column":53}},{"generated":{"line":207,"column":54},"source":"scripts\\model.js","original":{"line":56,"column":44}},{"generated":{"line":207,"column":55},"source":"scripts\\model.js","original":{"line":56,"column":21}},{"generated":{"line":207,"column":56},"source":"scripts\\model.js","original":{"line":56,"column":8}},{"generated":{"line":207,"column":57},"source":"scripts\\model.js","original":{"line":55,"column":37}},{"generated":{"line":207,"column":58},"source":"scripts\\model.js","original":{"line":56,"column":60}},{"generated":{"line":208,"column":0},"source":"scripts\\model.js","original":{"line":57,"column":8}},{"name":"rgbData","generated":{"line":208,"column":12},"source":"scripts\\model.js","original":{"line":57,"column":14}},{"name":"tf","generated":{"line":208,"column":22},"source":"scripts\\model.js","original":{"line":57,"column":24}},{"name":"stack","generated":{"line":208,"column":25},"source":"scripts\\model.js","original":{"line":57,"column":27}},{"generated":{"line":208,"column":30},"source":"scripts\\model.js","original":{"line":57,"column":24}},{"generated":{"line":208,"column":31},"source":"scripts\\model.js","original":{"line":57,"column":33}},{"name":"data","generated":{"line":208,"column":32},"source":"scripts\\model.js","original":{"line":57,"column":34}},{"generated":{"line":208,"column":36},"source":"scripts\\model.js","original":{"line":57,"column":33}},{"name":"data","generated":{"line":208,"column":38},"source":"scripts\\model.js","original":{"line":57,"column":40}},{"generated":{"line":208,"column":42},"source":"scripts\\model.js","original":{"line":57,"column":33}},{"name":"data","generated":{"line":208,"column":44},"source":"scripts\\model.js","original":{"line":57,"column":46}},{"generated":{"line":208,"column":48},"source":"scripts\\model.js","original":{"line":57,"column":33}},{"generated":{"line":208,"column":49},"source":"scripts\\model.js","original":{"line":57,"column":24}},{"generated":{"line":208,"column":51},"source":"scripts\\model.js","original":{"line":57,"column":53}},{"generated":{"line":208,"column":52},"source":"scripts\\model.js","original":{"line":57,"column":24}},{"generated":{"line":208,"column":53},"source":"scripts\\model.js","original":{"line":57,"column":8}},{"generated":{"line":208,"column":54},"source":"scripts\\model.js","original":{"line":55,"column":37}},{"generated":{"line":208,"column":55},"source":"scripts\\model.js","original":{"line":57,"column":60}},{"generated":{"line":209,"column":0},"source":"scripts\\model.js","original":{"line":58,"column":8}},{"name":"activation","generated":{"line":209,"column":12},"source":"scripts\\model.js","original":{"line":58,"column":14}},{"name":"truncModel","generated":{"line":209,"column":25},"source":"scripts\\model.js","original":{"line":58,"column":28}},{"name":"predict","generated":{"line":209,"column":36},"source":"scripts\\model.js","original":{"line":58,"column":39}},{"generated":{"line":209,"column":43},"source":"scripts\\model.js","original":{"line":58,"column":28}},{"name":"rgbData","generated":{"line":209,"column":44},"source":"scripts\\model.js","original":{"line":58,"column":47}},{"generated":{"line":209,"column":51},"source":"scripts\\model.js","original":{"line":58,"column":28}},{"generated":{"line":209,"column":52},"source":"scripts\\model.js","original":{"line":58,"column":8}},{"generated":{"line":210,"column":0},"source":"scripts\\model.js","original":{"line":59,"column":8}},{"name":"activation","generated":{"line":210,"column":15},"source":"scripts\\model.js","original":{"line":59,"column":15}},{"generated":{"line":210,"column":25},"source":"scripts\\model.js","original":{"line":59,"column":8}},{"generated":{"line":211,"column":0},"source":"scripts\\model.js","original":{"line":60,"column":5}},{"generated":{"line":211,"column":5},"source":"scripts\\model.js","original":{"line":55,"column":23}},{"generated":{"line":211,"column":6},"source":"scripts\\model.js","original":{"line":55,"column":4}},{"generated":{"line":213,"column":0},"source":"scripts\\model.js","original":{"line":62,"column":4}},{"name":"activation","generated":{"line":213,"column":11},"source":"scripts\\model.js","original":{"line":62,"column":11}},{"generated":{"line":213,"column":21},"source":"scripts\\model.js","original":{"line":62,"column":4}},{"generated":{"line":214,"column":0},"source":"scripts\\model.js","original":{"line":63,"column":1}}],"sources":{"scripts\\model.js":"import * as tf from '@tensorflow/tfjs';\r\nimport {\r\n    GENRES, GENRES_NUM, MUSIC_NUM_PER_GENRE,\r\n    FREQ_NUM, PROCESS_NUM,\r\n    PRED_BATCH_SIZE, TRAIN_BATCH_SIZE,\r\n} from './config.js';\r\n\r\nimport {myDataset} from './data'\r\n\r\n\r\nconst MODEL_URL = 'http://localhost:3000/truncated_model/tensorflowjs_model.pb'; \r\nconst WEIGHTS_URL = 'http://localhost:3000/truncated_model/weights_manifest.json'; \r\n\r\nlet model;\r\nlet truncModel;\r\n\r\nmodel = tf.sequential({\r\n    layers: [\r\n      // Flattens the input to a vector so we can use it in a dense layer. While\r\n      // technically a layer, this only performs a reshape (and has no training\r\n      // parameters).\r\n      tf.layers.flatten({inputShape: [4, 4, 1024]}),\r\n      // Layer 1\r\n      tf.layers.dense({\r\n        units: 256,           // 1024 is too large for tf.js \r\n        activation: 'relu',\r\n        kernelInitializer: 'varianceScaling',\r\n        useBias: true\r\n      }),\r\n      // Layer 2. The number of units of the last layer should correspond\r\n      // to the number of classes we want to predict.\r\n      tf.layers.dense({\r\n        units: GENRES_NUM,\r\n        kernelInitializer: 'varianceScaling',\r\n        useBias: false,\r\n        activation: 'softmax'\r\n      })\r\n    ]\r\n});\r\n\r\nconst optimizer = tf.train.rmsprop(0.00001); // 0.1 is too big, loss will oscillate in result \r\nmodel.compile({optimizer: optimizer, loss: 'categoricalCrossentropy'});\r\n\r\n\r\n\r\nexport async function loadMobileNet() {\r\n    truncModel =  await tf.loadFrozenModel(MODEL_URL, WEIGHTS_URL);\r\n    //warm up ??\r\n} \r\n\r\n\r\n\r\nexport function getActivation (dataArray) { // will activation be dispose??\r\n\r\n    const activation = tf.tidy(() => {\r\n        const data = tf.tensor3d(dataArray, [1, 128, 128]); // arr --> tensor\r\n        const rgbData = tf.stack([data, data, data], 3);    // --> 3 rgb channel [1, 128,]\r\n        const activation =  truncModel.predict(rgbData);\r\n        return activation;\r\n    });\r\n\r\n    return activation;\r\n}\r\n\r\n\r\n\r\nexport async function predict(dataArray) {\r\n\r\n    const predictedClass = tf.tidy(() => {\r\n        const activation =  getActivation(dataArray);\r\n        const predictions = model.predict(activation);\r\n        myDataset.addHistory(predictions);\r\n        return predictions.as1D().argMax();\r\n      });\r\n  \r\n      const classId = (await predictedClass.data())[0];\r\n      predictedClass.dispose();\r\n      console.log(classId);\r\n      return classId;\r\n   \r\n    \r\n} \r\n\r\n\r\n\r\nexport async function train(dataset, setLines) {\r\n \r\n    model.fit(dataset.xs, dataset.ys, {\r\n            validationSplit: 0.1, \r\n            batchSize: 5, \r\n            epochs: 10,\r\n            callbacks: {\r\n                onEpochEnd: async (epoch, logs) => {\r\n                    console.log(logs, epoch);\r\n                    setLines(logs.loss, logs.val_loss, epoch);\r\n                    await tf.nextFrame();\r\n                },\r\n                onBatchEnd: async (batch, logs) => {\r\n                    console.log(logs);\r\n                  console.log('Loss: ' + logs.loss.toFixed(5));\r\n                  await tf.nextFrame();\r\n                }\r\n            }\r\n        }\r\n    );\r\n\r\n}"},"lineCount":null}},"hash":"f4d4b0e56dd8d571d11948a340454551","cacheData":{"env":{}}}